audacianumberrecognition/AudaciaNumberRecognition.py
audacianumberrecognition/__init__.py
audacianumberrecognition-0.0.3.dist-info/LICENSE
audacianumberrecognition-0.0.3.dist-info/METADATA
audacianumberrecognition-0.0.3.dist-info/WHEEL
audacianumberrecognition-0.0.3.dist-info/top_level.txt
audacianumberrecognition-0.0.3.dist-info/RECORD
